{"title":"UTC","uid":"5b2670c5f5c997faf561bd54972c13be","slug":"UTC","date":"2023-07-07T17:47:16.115Z","updated":"2023-07-07T17:47:16.253Z","comments":true,"path":"api/articles/UTC.json","keywords":null,"cover":null,"content":"<blockquote><span class=\"custom-blockquote-svg\"><svg width=\"24\" height=\"24\" viewBox=\"0 0 24 24\" fill=\"\" xmlns=\"http://www.w3.org/2000/svg\" data-reactroot=\"\">\n<path fill=\"\" d=\"M22 12C22 6.5 17.5 2 12 2C6.5 2 2 6.5 2 12C2 17.5 6.5 22 12 22C13.8 22 15.5 21.5 17 20.6L22 22L20.7 17C21.5 15.5 22 13.8 22 12Z\" undefined=\"1\"></path>\n<path fill=\"\" d=\"M15.97 11.5H16.04C17.12 11.5 18 12.38 18 13.47V13.53C18 14.62 17.12 15.5 16.03 15.5H15.96C14.88 15.5 14 14.62 14 13.53V13.46C14 12.38 14.88 11.5 15.97 11.5Z\" undefined=\"1\"></path>\n<path fill=\"\" d=\"M7.97 11.5H8.04C9.12 11.5 10 12.38 10 13.47V13.53C10 14.62 9.12 15.5 8.03 15.5H7.97C6.88 15.5 6 14.62 6 13.53V13.46C6 12.38 6.88 11.5 7.97 11.5Z\" undefined=\"1\"></path>\n<path stroke-linejoin=\"round\" stroke-linecap=\"round\" stroke-miterlimit=\"10\" stroke-width=\"2\" stroke=\"\" d=\"M17 8.5C15.23 8.97 14.07 10.84 14.01 13.27C14 13.33 14 13.4 14 13.47V13.5\"></path>\n<path stroke-linejoin=\"round\" stroke-linecap=\"round\" stroke-miterlimit=\"10\" stroke-width=\"2\" stroke=\"\" d=\"M9 8.5C7.23 8.97 6.07 10.84 6.01 13.27C6 13.33 6 13.4 6 13.47V13.5\"></path>\n<path stroke-linejoin=\"round\" stroke-linecap=\"round\" stroke-miterlimit=\"10\" stroke-width=\"2\" stroke=\"\" d=\"M15.97 11.5H16.04C17.12 11.5 18 12.38 18 13.47V13.53C18 14.62 17.12 15.5 16.03 15.5H15.96C14.88 15.5 14 14.62 14 13.53V13.46C14 12.38 14.88 11.5 15.97 11.5Z\"></path>\n<path stroke-linejoin=\"round\" stroke-linecap=\"round\" stroke-miterlimit=\"10\" stroke-width=\"2\" stroke=\"\" d=\"M7.97 11.5H8.04C9.12 11.5 10 12.38 10 13.47V13.53C10 14.62 9.12 15.5 8.03 15.5H7.97C6.88 15.5 6 14.62 6 13.53V13.46C6 12.38 6.88 11.5 7.97 11.5Z\"></path>\n</svg>\n</span><p>协调世界时，又称世界统一时间、世界标准时间、国际协调时间。由于英文（CUT）和法文（TUC）的缩写不同，作为妥协，简称 UTC。协调世界时是以 原子时秒长为基础</p></blockquote>\n<h1 id=\"定义\"><a href=\"#定义\" class=\"headerlink\" title=\"定义\"></a>定义</h1><blockquote><span class=\"custom-blockquote-svg\"><svg width=\"24\" height=\"24\" viewBox=\"0 0 24 24\" fill=\"\" xmlns=\"http://www.w3.org/2000/svg\" data-reactroot=\"\">\n<path fill=\"\" d=\"M22 12C22 6.5 17.5 2 12 2C6.5 2 2 6.5 2 12C2 17.5 6.5 22 12 22C13.8 22 15.5 21.5 17 20.6L22 22L20.7 17C21.5 15.5 22 13.8 22 12Z\" undefined=\"1\"></path>\n<path fill=\"\" d=\"M15.97 11.5H16.04C17.12 11.5 18 12.38 18 13.47V13.53C18 14.62 17.12 15.5 16.03 15.5H15.96C14.88 15.5 14 14.62 14 13.53V13.46C14 12.38 14.88 11.5 15.97 11.5Z\" undefined=\"1\"></path>\n<path fill=\"\" d=\"M7.97 11.5H8.04C9.12 11.5 10 12.38 10 13.47V13.53C10 14.62 9.12 15.5 8.03 15.5H7.97C6.88 15.5 6 14.62 6 13.53V13.46C6 12.38 6.88 11.5 7.97 11.5Z\" undefined=\"1\"></path>\n<path stroke-linejoin=\"round\" stroke-linecap=\"round\" stroke-miterlimit=\"10\" stroke-width=\"2\" stroke=\"\" d=\"M17 8.5C15.23 8.97 14.07 10.84 14.01 13.27C14 13.33 14 13.4 14 13.47V13.5\"></path>\n<path stroke-linejoin=\"round\" stroke-linecap=\"round\" stroke-miterlimit=\"10\" stroke-width=\"2\" stroke=\"\" d=\"M9 8.5C7.23 8.97 6.07 10.84 6.01 13.27C6 13.33 6 13.4 6 13.47V13.5\"></path>\n<path stroke-linejoin=\"round\" stroke-linecap=\"round\" stroke-miterlimit=\"10\" stroke-width=\"2\" stroke=\"\" d=\"M15.97 11.5H16.04C17.12 11.5 18 12.38 18 13.47V13.53C18 14.62 17.12 15.5 16.03 15.5H15.96C14.88 15.5 14 14.62 14 13.53V13.46C14 12.38 14.88 11.5 15.97 11.5Z\"></path>\n<path stroke-linejoin=\"round\" stroke-linecap=\"round\" stroke-miterlimit=\"10\" stroke-width=\"2\" stroke=\"\" d=\"M7.97 11.5H8.04C9.12 11.5 10 12.38 10 13.47V13.53C10 14.62 9.12 15.5 8.03 15.5H7.97C6.88 15.5 6 14.62 6 13.53V13.46C6 12.38 6.88 11.5 7.97 11.5Z\"></path>\n</svg>\n</span><p>国际原子时的准确度为每日数纳秒，而世界时的准确度为每日数毫秒。许多应用部门要求时间系统接近世界时 UT，对于这种情况，一种称为协调世界时的折中时标于 1972 年面世。为确保协调世界时与世界时相差不会超过 0.9 秒，在有需要的情况下会在协调世界时内加上正或负闰秒。因此协调世界时与国际原子时之间会出现若干整数秒的差别，两者之差逐年积累，便采用跳秒（闰秒）的方法使协调时与世界时的时刻相接近，其差不超过 1s。它既保持时间尺度的均匀性，又能近似地反映地球自转的变化。按国际无线电咨询委员会（CCIR）通过的关于 UTC 的修正案，从 1972 年 1 月 1 日起 UTC 与 UT1（在 UT 中加入极移改正得到）之间的差值最大可以达到±0.9s。位于巴黎的国际地球自转事务中央局负责决定何时加入闰秒。一般会在每年的 6 月 30 日、12 月 31 日的最后一秒进行调整。</p></blockquote>\n","text":" 协调世界时，又称世界统一时间、世界标准时间、国际协调时间。由于英文（CUT）和法文（TUC）的缩写不同，作为妥协，简称 UTC。协调世界时是以 原子时秒长为基础 定义 国际原子时的准确度为每日数纳秒，而世界时的准确度为每日数毫秒。许多应用部门要求时间系统接近世界时 UT，对于这...","link":"","photos":[],"count_time":{"symbolsCount":490,"symbolsTime":"1 mins."},"categories":[],"tags":[],"toc":"<ol class=\"toc\"><li class=\"toc-item toc-level-1\"><a class=\"toc-link\" href=\"#%E5%AE%9A%E4%B9%89\"><span class=\"toc-text\">定义</span></a></li></ol>","author":{"name":"Devmacy","slug":"blog-author","avatar":"https://s1.ax1x.com/2023/01/24/pSYhwB4.jpg","link":"/","description":"数字花园","socials":{"github":"https://github.com/Devmacy","twitter":"","stackoverflow":"","wechat":"","qq":"","weibo":"","zhihu":"","csdn":"","juejin":"","customs":{}}},"mapped":true,"prev_post":{"title":"video","uid":"aa00fa048ffbfbd0057cd5b16da9e258","slug":"video","date":"2023-07-07T17:47:16.117Z","updated":"2023-07-07T17:47:16.254Z","comments":true,"path":"api/articles/video.json","keywords":null,"cover":null,"text":"#HTML 定义 HTML &lt;video&gt; 元素 用于在 HTML 或者 XHTML 文档中嵌入媒体播放器，用于支持文档内的视频播放 示例&lt;video controls width=\"250\"> &lt;source src=\"/media/cc0videos/...","link":"","photos":[],"count_time":{"symbolsCount":262,"symbolsTime":"1 mins."},"categories":[],"tags":[{"name":"HTML","slug":"HTML","count":14,"path":"api/tags/HTML.json"}],"author":{"name":"Devmacy","slug":"blog-author","avatar":"https://s1.ax1x.com/2023/01/24/pSYhwB4.jpg","link":"/","description":"数字花园","socials":{"github":"https://github.com/Devmacy","twitter":"","stackoverflow":"","wechat":"","qq":"","weibo":"","zhihu":"","csdn":"","juejin":"","customs":{}}}},"next_post":{"title":"TypeScript装饰器","uid":"6ce48bf08a6702c21eabf4f22bcbbe7d","slug":"TypeScript装饰器","date":"2023-07-07T17:47:16.113Z","updated":"2023-07-07T17:47:16.253Z","comments":true,"path":"api/articles/TypeScript装饰器.json","keywords":null,"cover":null,"text":"#TypeScript TypeScript 装饰器是一种特殊类型的声明，它可以附加到类、方法、属性或参数上，以修改或增强它们的行为。装饰器提供了一种在不修改源代码的情况下对现有代码进行扩展的机制。 分类类装饰器\"compilerOptions\": &#123; \"experim...","link":"","photos":[],"count_time":{"symbolsCount":"1.9k","symbolsTime":"2 mins."},"categories":[],"tags":[{"name":"TypeScript","slug":"TypeScript","count":6,"path":"api/tags/TypeScript.json"}],"author":{"name":"Devmacy","slug":"blog-author","avatar":"https://s1.ax1x.com/2023/01/24/pSYhwB4.jpg","link":"/","description":"数字花园","socials":{"github":"https://github.com/Devmacy","twitter":"","stackoverflow":"","wechat":"","qq":"","weibo":"","zhihu":"","csdn":"","juejin":"","customs":{}}}}}