{"title":"设计文档","uid":"c87aeab67940360853b19fd40dd01a68","slug":"设计文档","date":"2023-07-07T17:47:16.182Z","updated":"2023-07-29T10:11:28.971Z","comments":true,"path":"api/articles/设计文档.json","keywords":"Digital Garden","cover":null,"content":"<h1 id=\"待办\"><a href=\"#待办\" class=\"headerlink\" title=\"待办\"></a>待办</h1><ul>\n<li><input checked=\"\" disabled=\"\" type=\"checkbox\"> 创建项目</li>\n<li><input checked=\"\" disabled=\"\" type=\"checkbox\"> 创建别名</li>\n</ul>\n<h1 id=\"功能\"><a href=\"#功能\" class=\"headerlink\" title=\"功能\"></a>功能</h1><ul>\n<li>功能聚合网站</li>\n<li>新奇创意</li>\n</ul>\n<h1 id=\"技术栈\"><a href=\"#技术栈\" class=\"headerlink\" title=\"技术栈\"></a>技术栈</h1><ul>\n<li>构建工具：<strong>vite</strong></li>\n<li>前端框架：<strong>vue3</strong></li>\n<li>编程语言：<strong>typescript</strong></li>\n<li>[[路由]] 工具：<strong>vuerouter</strong></li>\n<li>状态管理：<strong>Pinia</strong></li>\n<li>UI 框架：<strong>ElementUI Plus</strong></li>\n<li>HTTP 工具：<strong>Axios</strong></li>\n<li>CSS 预编译：**[[Sass]]**</li>\n<li>自动部署：<strong>Github Actions</strong></li>\n<li>编码规范：<strong>standard-with-typescript</strong></li>\n<li>代码测试：<strong>vitest</strong></li>\n<li>代码检查：<strong>eslint</strong></li>\n</ul>\n<h1 id=\"命名规范\"><a href=\"#命名规范\" class=\"headerlink\" title=\"命名规范\"></a>命名规范</h1><h2 id=\"文件夹命名\"><a href=\"#文件夹命名\" class=\"headerlink\" title=\"文件夹命名\"></a>文件夹命名</h2><h3 id=\"多个单词\"><a href=\"#多个单词\" class=\"headerlink\" title=\"多个单词\"></a>多个单词</h3><p>小驼峰</p>\n<h3 id=\"单个单词\"><a href=\"#单个单词\" class=\"headerlink\" title=\"单个单词\"></a>单个单词</h3><p>小驼峰</p>\n<h3 id=\"文件命名\"><a href=\"#文件命名\" class=\"headerlink\" title=\"文件命名\"></a>文件命名</h3><h4 id=\"组件\"><a href=\"#组件\" class=\"headerlink\" title=\"组件\"></a>组件</h4><p>大驼峰</p>\n<h4 id=\"其他\"><a href=\"#其他\" class=\"headerlink\" title=\"其他\"></a>其他</h4><p> 小驼峰</p>\n<h1 id=\"颜色组\"><a href=\"#颜色组\" class=\"headerlink\" title=\"颜色组\"></a>颜色组</h1><h1 id=\"页面布局\"><a href=\"#页面布局\" class=\"headerlink\" title=\"页面布局\"></a>页面布局</h1><h1 id=\"项目目录\"><a href=\"#项目目录\" class=\"headerlink\" title=\"项目目录\"></a>项目目录</h1><ol>\n<li><strong>router</strong> 路由文件夹</li>\n<li><strong>components</strong> 公共组件文件夹<ol>\n<li><strong>layout</strong> 页面布局文件夹</li>\n</ol>\n</li>\n<li><strong>views</strong> 页面文件夹<ol>\n<li><strong>components</strong> 页面组件文件夹</li>\n</ol>\n</li>\n<li><strong>store</strong> 状态管理文件夹</li>\n<li><strong>config</strong> 项目公共配置文件夹</li>\n<li><strong>utils</strong> 工具文件夹</li>\n<li><strong>test</strong> 测试文件夹</li>\n<li><strong>styles</strong> 公共样式文件夹</li>\n<li><strong>api</strong> 接口文件夹</li>\n<li><strong>assets</strong> 资源文件夹</li>\n<li><strong>@types</strong> 类型文件夹</li>\n</ol>\n","text":"待办 创建项目 创建别名 功能 功能聚合网站 新奇创意 技术栈 构建工具：vite 前端框架：vue3 编程语言：typescript [[路由]] 工具：vuerouter 状态管理：Pinia UI 框架：ElementUI Plus HTTP 工具：Axios CSS 预编...","link":"","photos":[],"count_time":{"symbolsCount":476,"symbolsTime":"1 mins."},"categories":[],"tags":[],"toc":"<ol class=\"toc\"><li class=\"toc-item toc-level-1\"><a class=\"toc-link\" href=\"#%E5%BE%85%E5%8A%9E\"><span class=\"toc-text\">待办</span></a></li><li class=\"toc-item toc-level-1\"><a class=\"toc-link\" href=\"#%E5%8A%9F%E8%83%BD\"><span class=\"toc-text\">功能</span></a></li><li class=\"toc-item toc-level-1\"><a class=\"toc-link\" href=\"#%E6%8A%80%E6%9C%AF%E6%A0%88\"><span class=\"toc-text\">技术栈</span></a></li><li class=\"toc-item toc-level-1\"><a class=\"toc-link\" href=\"#%E5%91%BD%E5%90%8D%E8%A7%84%E8%8C%83\"><span class=\"toc-text\">命名规范</span></a><ol class=\"toc-child\"><li class=\"toc-item toc-level-2\"><a class=\"toc-link\" href=\"#%E6%96%87%E4%BB%B6%E5%A4%B9%E5%91%BD%E5%90%8D\"><span class=\"toc-text\">文件夹命名</span></a><ol class=\"toc-child\"><li class=\"toc-item toc-level-3\"><a class=\"toc-link\" href=\"#%E5%A4%9A%E4%B8%AA%E5%8D%95%E8%AF%8D\"><span class=\"toc-text\">多个单词</span></a></li><li class=\"toc-item toc-level-3\"><a class=\"toc-link\" href=\"#%E5%8D%95%E4%B8%AA%E5%8D%95%E8%AF%8D\"><span class=\"toc-text\">单个单词</span></a></li><li class=\"toc-item toc-level-3\"><a class=\"toc-link\" href=\"#%E6%96%87%E4%BB%B6%E5%91%BD%E5%90%8D\"><span class=\"toc-text\">文件命名</span></a><ol class=\"toc-child\"><li class=\"toc-item toc-level-4\"><a class=\"toc-link\" href=\"#%E7%BB%84%E4%BB%B6\"><span class=\"toc-text\">组件</span></a></li><li class=\"toc-item toc-level-4\"><a class=\"toc-link\" href=\"#%E5%85%B6%E4%BB%96\"><span class=\"toc-text\">其他</span></a></li></ol></li></ol></li></ol></li><li class=\"toc-item toc-level-1\"><a class=\"toc-link\" href=\"#%E9%A2%9C%E8%89%B2%E7%BB%84\"><span class=\"toc-text\">颜色组</span></a></li><li class=\"toc-item toc-level-1\"><a class=\"toc-link\" href=\"#%E9%A1%B5%E9%9D%A2%E5%B8%83%E5%B1%80\"><span class=\"toc-text\">页面布局</span></a></li><li class=\"toc-item toc-level-1\"><a class=\"toc-link\" href=\"#%E9%A1%B9%E7%9B%AE%E7%9B%AE%E5%BD%95\"><span class=\"toc-text\">项目目录</span></a></li></ol>","author":{"name":"Devmacy","slug":"blog-author","avatar":"https://s1.ax1x.com/2023/01/24/pSYhwB4.jpg","link":"/","description":"数字花园","socials":{"github":"https://github.com/Devmacy","twitter":"","stackoverflow":"","wechat":"","qq":"","weibo":"","zhihu":"","csdn":"","juejin":"","customs":{}}},"mapped":true,"prev_post":{"title":"贝赛尔曲线","uid":"174af5369df658c708e4ac6b59c60cb4","slug":"贝赛尔曲线","date":"2023-07-07T17:47:16.185Z","updated":"2023-07-29T10:11:28.972Z","comments":true,"path":"api/articles/贝赛尔曲线.json","keywords":"Digital Garden","cover":null,"text":"定义 Bézier curve(贝塞尔曲线) 是应用于二维图形应用程序的数学曲线 伯恩斯坦多项式 可以用来证明，在 [a, b] 区间上所有的连续函数都可以用多项式来逼近，并且收敛性很强，也就是一致收敛 拟合原理-AD/AB = BE/BC = DF/DE ","link":"","photos":[],"count_time":{"symbolsCount":145,"symbolsTime":"1 mins."},"categories":[],"tags":[],"author":{"name":"Devmacy","slug":"blog-author","avatar":"https://s1.ax1x.com/2023/01/24/pSYhwB4.jpg","link":"/","description":"数字花园","socials":{"github":"https://github.com/Devmacy","twitter":"","stackoverflow":"","wechat":"","qq":"","weibo":"","zhihu":"","csdn":"","juejin":"","customs":{}}}},"next_post":{"title":"记录用户操作轨迹","uid":"a8c55f11a67107e06781ca4751b6c9dc","slug":"记录用户操作轨迹","date":"2023-07-07T17:47:16.180Z","updated":"2023-07-29T10:11:28.971Z","comments":true,"path":"api/articles/记录用户操作轨迹.json","keywords":"Digital Garden","cover":null,"text":"记录用户操作轨迹涉及用户隐私问题，您应该在收集和存储用户数据时遵循适当的隐私政策，并确保对数据进行安全保护。此外，在实施此功能之前，建议与法律和隐私专家进行咨询，以确保您的实施符合适用的法律要求 记录前端监控添加监控脚本，捕获用户交互行为，例如点击，滚动，输入，并将信息发送到服务...","link":"","photos":[],"count_time":{"symbolsCount":302,"symbolsTime":"1 mins."},"categories":[],"tags":[],"author":{"name":"Devmacy","slug":"blog-author","avatar":"https://s1.ax1x.com/2023/01/24/pSYhwB4.jpg","link":"/","description":"数字花园","socials":{"github":"https://github.com/Devmacy","twitter":"","stackoverflow":"","wechat":"","qq":"","weibo":"","zhihu":"","csdn":"","juejin":"","customs":{}}}}}